trust_track_api/__init__.py
trust_track_api/truck.py
trust_track_api/trust_track_api.py
trust_track_api-0.9.4.dist-info/METADATA
trust_track_api-0.9.4.dist-info/WHEEL
trust_track_api-0.9.4.dist-info/top_level.txt
trust_track_api-0.9.4.dist-info/RECORD
