Metadata-Version: 2.1
Name: trust-track-api
Version: 0.9.4
Summary: TrustTrack Ruptela API Wrapper
Home-page: 
Author: Lyubomir Traykov
Author-email: lyubomir.traykov@traykovtrans.com
Requires-Dist: requests-cache
Requires-Dist: pytz
